feincms_mailchimp/__init__.py
feincms_mailchimp/apps.py
feincms_mailchimp/models.py
feincms_mailchimp/urls.py
feincms_mailchimp/views.py
feincms_mailchimp/locale/ru/LC_MESSAGES/django.mo
feincms_mailchimp/locale/ru/LC_MESSAGES/django.po
feincms_mailchimp/static/css/feincms_mailchimp.css
feincms_mailchimp/static/js/feincms_mailchimp.js
feincms_mailchimp/templates/feincms_mailchimp/base.html
feincms_mailchimp/templates/feincms_mailchimp/base.html.py
feincms_mailchimp/templates/feincms_mailchimp/signup.html
feincms_mailchimp/templates/feincms_mailchimp/signup.html.py
feincms_mailchimp-0.1.6.dist-info/DESCRIPTION.rst
feincms_mailchimp-0.1.6.dist-info/METADATA
feincms_mailchimp-0.1.6.dist-info/RECORD
feincms_mailchimp-0.1.6.dist-info/SOURCES.txt.py
feincms_mailchimp-0.1.6.dist-info/WHEEL
feincms_mailchimp-0.1.6.dist-info/dependency_links.txt.py
feincms_mailchimp-0.1.6.dist-info/metadata.json
feincms_mailchimp-0.1.6.dist-info/requires.txt.py
feincms_mailchimp-0.1.6.dist-info/top_level.txt
feincms_mailchimp-0.1.6.dist-info/top_level.txt.py
